ompute/__init__.py
ompute/model/aenc.py
ompute/model/bayreg.py
ompute/model/enet.py
ompute/model/expmax.py
ompute/model/hotdeck.py
ompute/model/knn.py
ompute/model/lls.py
ompute/model/mean.py
ompute/model/median.py
ompute/model/mice.py
ompute/model/mindet.py
ompute/model/minprob.py
ompute/model/missforest.py
ompute/model/missmda.py
ompute/model/mode.py
ompute/model/pdn.py
ompute/model/ppca.py
ompute/model/qrilc.py
ompute/model/rnf.py
ompute/model/sfi.py
ompute/model/svd.py
ompute/model/tni.py
ompute/model/trb1.py
ompute/model/trb10.py
ompute/model/trb2.py
ompute/model/trb3.py
ompute/model/trb4.py
ompute/model/trb5.py
ompute/model/trb6.py
ompute/model/trb7.py
ompute/model/trb8.py
ompute/model/trb9.py
ompute-1.0.0.dist-info/METADATA
ompute-1.0.0.dist-info/WHEEL
ompute-1.0.0.dist-info/top_level.txt
ompute-1.0.0.dist-info/RECORD
