Metadata-Version: 2.4
Name: ompute
Version: 1.0.0
Summary: Python package for Biological Omics Data Missing Value Imputation
Author-email: Sanjay S <thy.sanjay@gmail.com>
License: MIT
Keywords: omics,imputation,proteomics,metabolomics,transcriptomics,missing-value
Classifier: Programming Language :: Python :: 3
Classifier: License :: OSI Approved :: MIT License
Classifier: Topic :: Scientific/Engineering :: Bio-Informatics
Requires-Python: >=3.8
Provides-Extra: full
Requires-Dist: pandas>=2.0.0; extra == "full"
Requires-Dist: numpy>=1.23.0; extra == "full"
Requires-Dist: scikit-learn>=1.3.0; extra == "full"
Requires-Dist: scipy>=1.10.0; extra == "full"
Requires-Dist: statsmodels>=0.14.0; extra == "full"
Requires-Dist: missingpy>=0.2.0; extra == "full"
Requires-Dist: fancyimpute>=0.7.0; extra == "full"
Requires-Dist: tensorflow>=2.12.0; extra == "full"
Requires-Dist: pymc>=5.0.0; extra == "full"
Requires-Dist: arviz>=0.16.0; extra == "full"
Requires-Dist: tqdm>=4.66.0; extra == "full"
